geotext/__init__.py
geotext/geotext.py
geotext/data/cities15000.txt
geotext/data/citypatches.txt
geotext/data/countryInfo.txt
geotext/data/nationalities.txt
geotext-0.4.0.dist-info/METADATA
geotext-0.4.0.dist-info/RECORD
geotext-0.4.0.dist-info/WHEEL
geotext-0.4.0.dist-info/top_level.txt
