Metadata-Version: 1.1
Name: geotext
Version: 0.4.0
Summary: Geotext extracts countriy and city mentions from text
Home-page: https://github.com/elyase/geotext
Author: Yaser Martinez Palenzuela
Author-email: yaser.martinez@gmail.com
License: MIT
Keywords: geotext
Platform: UNKNOWN
Classifier: Intended Audience :: Developers
Classifier: License :: OSI Approved :: MIT License
Classifier: Programming Language :: Python :: 2.7
Classifier: Programming Language :: Python :: 3.5
Classifier: Programming Language :: Python :: 3.6
